takeltest/__init__.py
takeltest/boilerplate.py
takeltest/moleculebook.py
takeltest/moleculeenv.py
takeltest/moleculeinventory.py
takeltest/multitestvars.py
takeltest/pathlist.py
takeltest/plugin.py
pytest_takeltest-0.12.7.dist-info/LICENSE
pytest_takeltest-0.12.7.dist-info/METADATA
pytest_takeltest-0.12.7.dist-info/WHEEL
pytest_takeltest-0.12.7.dist-info/entry_points.txt
pytest_takeltest-0.12.7.dist-info/top_level.txt
pytest_takeltest-0.12.7.dist-info/RECORD
