Metadata-Version: 2.1
Name: pytest-takeltest
Version: 0.12.7
Summary: Fixtures for ansible, testinfra and molecule
Home-page: https://github.com/takelwerk/takelage-var
Author: Takelwerk
Author-email: takeltest@takelwerk.net
License: GPLv3
Platform: any
Classifier: Programming Language :: Python
Classifier: Programming Language :: Python :: 3
Classifier: Intended Audience :: Information Technology
Classifier: Intended Audience :: Developers
Classifier: Intended Audience :: System Administrators
Classifier: License :: OSI Approved :: MIT License
Classifier: Operating System :: POSIX
Classifier: Topic :: Software Development :: Libraries :: Python Modules
Classifier: Topic :: Software Development :: Testing
Classifier: Topic :: System :: Systems Administration
Classifier: Framework :: Pytest
License-File: LICENSE
Requires-Dist: ansible (>=2.8)
